summer2/__init__.py
summer2/adjust.py
summer2/compartment.py
summer2/compute_bak/__init__.py
summer2/compute_bak/compute_jax.py
summer2/derived_outputs.py
summer2/experimental/model_builder.py
summer2/extras/test_models.py
summer2/flows.py
summer2/functions/__init__.py
summer2/functions/derived.py
summer2/functions/interpolate.py
summer2/functions/interpolate_old.py
summer2/functions/time.py
summer2/functions/util.py
summer2/inspect.py
summer2/model.py
summer2/parameters/__init__.py
summer2/parameters/param_impl.py
summer2/parameters/params.py
summer2/parameters/support.py
summer2/population.py
summer2/runner/__init__.py
summer2/runner/jax/__init__.py
summer2/runner/jax/derived_outputs.py
summer2/runner/jax/model_impl.py
summer2/runner/jax/ode.py
summer2/runner/jax/ode2.py
summer2/runner/jax/solvers.py
summer2/runner/jax/stratify.py
summer2/runner/model_runner.py
summer2/solver.py
summer2/stratification.py
summer2/tracker.py
summer2/utils.py
summerepi2-1.3.6.dist-info/LICENSE.txt
summerepi2-1.3.6.dist-info/METADATA
summerepi2-1.3.6.dist-info/WHEEL
summerepi2-1.3.6.dist-info/RECORD
