Metadata-Version: 2.1
Name: summerepi2
Version: 1.3.6
Summary: Summer is a compartmental disease modelling framework, written in Python. It provides a high-level API to build and run models.
Home-page: https://github.com/monash-emu/summer2
License: BSD-2-Clause
Keywords: epidemiology,disease,compartmental,infectious
Author: David Shipman
Author-email: dshipman@gmail.com
Requires-Python: >=3.10.0
Classifier: License :: OSI Approved :: BSD License
Classifier: Programming Language :: Python :: 3
Classifier: Programming Language :: Python :: 3.10
Classifier: Programming Language :: Python :: 3.11
Provides-Extra: docs
Requires-Dist: computegraph (==0.4.5)
Requires-Dist: ipykernel (>=6.15.1,<7.0.0) ; extra == "docs"
Requires-Dist: jax (>=0.4.24)
Requires-Dist: jaxlib (>=0.4.24)
Requires-Dist: matplotlib (>=3.4.3) ; extra == "docs"
Requires-Dist: nbsphinx (>=0.8.2,<0.9.0) ; extra == "docs"
Requires-Dist: networkx (>=2.6.2)
Requires-Dist: numpy (>=1.20.3)
Requires-Dist: pandas (>=1.3.2)
Requires-Dist: plotly (>=5.5.0)
Requires-Dist: pygraphviz (>=1.10,<2.0) ; extra == "docs"
Requires-Dist: recommonmark (>=0.7.1,<0.8.0) ; extra == "docs"
Requires-Dist: sphinx-rtd-theme (>=0.5.1,<0.6.0) ; extra == "docs"
Requires-Dist: sphinxcontrib-napoleon (>=0.7,<0.8) ; extra == "docs"
Project-URL: Documentation, https://summer2.readthedocs.io/en/latest/
Project-URL: Repository, https://github.com/monash-emu/summer2
